neo_pusher/__init__.py
neo_pusher/agent.py
neo_pusher/get_link.py
test/__init__.py
test/test.py
neo_pusher-1.1.3.dist-info/LICENSE.md
neo_pusher-1.1.3.dist-info/METADATA
neo_pusher-1.1.3.dist-info/WHEEL
neo_pusher-1.1.3.dist-info/top_level.txt
neo_pusher-1.1.3.dist-info/RECORD
