Metadata-Version: 2.1
Name: neo-pusher
Version: 1.1.3
Summary: A package for Neo4j data ingestion using an AI agent.
Author: Mindfire Digital LLP
Author-email: siddharthc@mindfiresolutions.com
Classifier: Programming Language :: Python :: 3
Classifier: License :: OSI Approved :: MIT License
Classifier: Operating System :: OS Independent
Requires-Python: >=3.10
License-File: LICENSE.md
Requires-Dist: langchain
Requires-Dist: langchain-experimental
Requires-Dist: langchain-openai
Requires-Dist: pandas
Requires-Dist: neo4j
